<?xml version="1.0" encoding="UTF-8"?>
<?xml-model href="http://pds.jpl.nasa.gov/pds4/pds/v1/PDS4_PDS_1301.sch" schematypens="http://purl.oclc.org/dsdl/schematron"?>
<Product_Context xmlns="http://pds.nasa.gov/pds4/pds/v1"
 xmlns:xsi="http://www.w3.org/2001/XMLSchema-instance"
 xsi:schemaLocation="http://pds.nasa.gov/pds4/pds/v1 http://pds.jpl.nasa.gov/pds4/pds/v1/PDS4_PDS_1301.xsd">

    <Identification_Area>
        <logical_identifier>urn:nasa:pds:context_pds3:resource:resource.lunar_crater_observation_and_sensing_satellite_archive_information</logical_identifier>
        <version_id>1.0</version_id>
        <title>Lunar Crater Observation And Sensing Satellite (LCROSS) Archive Information</title>
        <information_model_version>1.3.0.1</information_model_version>
        <product_class>Product_Context</product_class>
        <Alias_List>
            <Alias>
                <alternate_title>LCROSS Archive Information</alternate_title>
            </Alias>
        </Alias_List>
        <Modification_History>
            <Modification_Detail>
                <modification_date>2014-11-29</modification_date>
                <version_id>1.0</version_id>
                <description>
                    Initial revision.
                </description>
            </Modification_Detail>
        </Modification_History>
    </Identification_Area>

    <Reference_List>
        <Internal_Reference>
            <lid_reference>urn:nasa:pds:context_pds3:investigation:mission.lunar_crater_observation_and_sensing_satellite</lid_reference>
            <reference_type>resource_to_investigation</reference_type>
        </Internal_Reference>
        <Internal_Reference>
            <lid_reference>urn:nasa:pds:context_pds3:instrument_host:earth-based.apo35m</lid_reference>
            <reference_type>resource_to_instrument_host</reference_type>
        </Internal_Reference>
        <Internal_Reference>
            <lid_reference>urn:nasa:pds:context_pds3:instrument_host:earth-based.mmto</lid_reference>
            <reference_type>resource_to_instrument_host</reference_type>
        </Internal_Reference>
        <Internal_Reference>
            <lid_reference>urn:nasa:pds:context_pds3:instrument_host:earth-based.mro24m</lid_reference>
            <reference_type>resource_to_instrument_host</reference_type>
        </Internal_Reference>
        <Internal_Reference>
            <lid_reference>urn:nasa:pds:context_pds3:instrument_host:earth-based.obs376t3</lid_reference>
            <reference_type>resource_to_instrument_host</reference_type>
        </Internal_Reference>
        <Internal_Reference>
            <lid_reference>urn:nasa:pds:context_pds3:instrument_host:earth-based.obs378t2</lid_reference>
            <reference_type>resource_to_instrument_host</reference_type>
        </Internal_Reference>
        <Internal_Reference>
            <lid_reference>urn:nasa:pds:context_pds3:instrument_host:spacecraft.lcross</lid_reference>
            <reference_type>resource_to_instrument_host</reference_type>
        </Internal_Reference>
        <Internal_Reference>
            <lid_reference>urn:nasa:pds:context_pds3:instrument:instrument.agile__apo35m</lid_reference>
            <reference_type>resource_to_instrument</reference_type>
        </Internal_Reference>
        <Internal_Reference>
            <lid_reference>urn:nasa:pds:context_pds3:instrument:instrument.ccd47__mmto</lid_reference>
            <reference_type>resource_to_instrument</reference_type>
        </Internal_Reference>
        <Internal_Reference>
            <lid_reference>urn:nasa:pds:context_pds3:instrument:instrument.clio__mmto</lid_reference>
            <reference_type>resource_to_instrument</reference_type>
        </Internal_Reference>
        <Internal_Reference>
            <lid_reference>urn:nasa:pds:context_pds3:instrument:instrument.cvf__obs376t3</lid_reference>
            <reference_type>resource_to_instrument</reference_type>
        </Internal_Reference>
        <Internal_Reference>
            <lid_reference>urn:nasa:pds:context_pds3:instrument:instrument.i0039__obs378t2</lid_reference>
            <reference_type>resource_to_instrument</reference_type>
        </Internal_Reference>
        <Internal_Reference>
            <lid_reference>urn:nasa:pds:context_pds3:instrument:instrument.i0046__obs376t3</lid_reference>
            <reference_type>resource_to_instrument</reference_type>
        </Internal_Reference>
        <Internal_Reference>
            <lid_reference>urn:nasa:pds:context_pds3:instrument:instrument.i0051__obs376t3</lid_reference>
            <reference_type>resource_to_instrument</reference_type>
        </Internal_Reference>
        <Internal_Reference>
            <lid_reference>urn:nasa:pds:context_pds3:instrument:instrument.i0070__obs376t3</lid_reference>
            <reference_type>resource_to_instrument</reference_type>
        </Internal_Reference>
        <Internal_Reference>
            <lid_reference>urn:nasa:pds:context_pds3:instrument:instrument.i0071__obs376t3</lid_reference>
            <reference_type>resource_to_instrument</reference_type>
        </Internal_Reference>
        <Internal_Reference>
            <lid_reference>urn:nasa:pds:context_pds3:instrument:instrument.mir1__lcross</lid_reference>
            <reference_type>resource_to_instrument</reference_type>
        </Internal_Reference>
        <Internal_Reference>
            <lid_reference>urn:nasa:pds:context_pds3:instrument:instrument.mir2__lcross</lid_reference>
            <reference_type>resource_to_instrument</reference_type>
        </Internal_Reference>
        <Internal_Reference>
            <lid_reference>urn:nasa:pds:context_pds3:instrument:instrument.nir1__lcross</lid_reference>
            <reference_type>resource_to_instrument</reference_type>
        </Internal_Reference>
        <Internal_Reference>
            <lid_reference>urn:nasa:pds:context_pds3:instrument:instrument.nir2__lcross</lid_reference>
            <reference_type>resource_to_instrument</reference_type>
        </Internal_Reference>
        <Internal_Reference>
            <lid_reference>urn:nasa:pds:context_pds3:instrument:instrument.nsp1__lcross</lid_reference>
            <reference_type>resource_to_instrument</reference_type>
        </Internal_Reference>
        <Internal_Reference>
            <lid_reference>urn:nasa:pds:context_pds3:instrument:instrument.nsp2__lcross</lid_reference>
            <reference_type>resource_to_instrument</reference_type>
        </Internal_Reference>
        <Internal_Reference>
            <lid_reference>urn:nasa:pds:context_pds3:instrument:instrument.photdoc__mro24m</lid_reference>
            <reference_type>resource_to_instrument</reference_type>
        </Internal_Reference>
        <Internal_Reference>
            <lid_reference>urn:nasa:pds:context_pds3:instrument:instrument.photgjon__mro24m</lid_reference>
            <reference_type>resource_to_instrument</reference_type>
        </Internal_Reference>
        <Internal_Reference>
            <lid_reference>urn:nasa:pds:context_pds3:instrument:instrument.tlp__lcross</lid_reference>
            <reference_type>resource_to_instrument</reference_type>
        </Internal_Reference>
        <Internal_Reference>
            <lid_reference>urn:nasa:pds:context_pds3:instrument:instrument.vis__lcross</lid_reference>
            <reference_type>resource_to_instrument</reference_type>
        </Internal_Reference>
        <Internal_Reference>
            <lid_reference>urn:nasa:pds:context_pds3:instrument:instrument.vsp__lcross</lid_reference>
            <reference_type>resource_to_instrument</reference_type>
        </Internal_Reference>
        <!-- Limited to primary targets for search purposes. -->
        <Internal_Reference>
            <lid_reference>urn:nasa:pds:context_pds3:target:star.1_aurigae</lid_reference>
            <reference_type>resource_to_target</reference_type>
        </Internal_Reference>
        <Internal_Reference>
            <lid_reference>urn:nasa:pds:context_pds3:target:star.68_psc</lid_reference>
            <reference_type>resource_to_target</reference_type>
        </Internal_Reference>
        <Internal_Reference>
            <lid_reference>urn:nasa:pds:context_pds3:target:calibration.bias</lid_reference>
            <reference_type>resource_to_target</reference_type>
        </Internal_Reference>
        <Internal_Reference>
            <lid_reference>urn:nasa:pds:context_pds3:target:planet.earth</lid_reference>
            <reference_type>resource_to_target</reference_type>
        </Internal_Reference>
        <Internal_Reference>
            <lid_reference>urn:nasa:pds:context_pds3:target:satellite.moon</lid_reference>
            <reference_type>resource_to_target</reference_type>
        </Internal_Reference>
    </Reference_List>

    <Resource>
        <name>Lunar Crater Observation And Sensing Satellite (LCROSS) Archive Information</name>
        <type>Information.Investigation</type>
        <url>http://pds-geosciences.wustl.edu/missions/lcross/default.htm</url>
        <description>
            The Lunar Crater Observation And Sensing Satellite (LCROSS) Archive Information page provides details on the investigation, instruments and targets associated with the archive as well as additional resources for discovering LCROSS data.
        </description>
    </Resource>
</Product_Context>
