<?xml version="1.0" encoding="UTF-8"?>
<?xml-model href="https://pds.nasa.gov/pds4/pds/v1/PDS4_PDS_1600.sch" schematypens="http://purl.oclc.org/dsdl/schematron"?>
<Product_Data_Set_PDS3 xmlns="http://pds.nasa.gov/pds4/pds/v1"
 xmlns:pds="http://pds.nasa.gov/pds4/pds/v1"  xmlns:xsi="http://www.w3.org/2001/XMLSchema-instance"
 xsi:schemaLocation="http://pds.nasa.gov/pds4/pds/v1 https://pds.nasa.gov/pds4/pds/v1/PDS4_PDS_1600.xsd">
    
    <Identification_Area>
        <logical_identifier>urn:nasa:pds:context_pds3:data_set:data_set.mex-m-omega-2-edr-flight-v1.0</logical_identifier>
        <version_id>1.0</version_id>
        <title>OMEGA FLIGHT EXPERIMENT DATA RECORDS</title>
        <information_model_version>1.6.0.0</information_model_version>
        <product_class>Product_Data_Set_PDS3</product_class>
        <Modification_History>
            <Modification_Detail>
                <modification_date>2016-10-01</modification_date>
                <version_id>1.0</version_id>
                <description>
                    extracted metadata from PDS3 catalog and
                    modified to comply with PDS4 Information Model
                </description>
            </Modification_Detail>
        </Modification_History>
    </Identification_Area>
    
    <Reference_List>
        <Internal_Reference>
            <lidvid_reference>urn:nasa:pds:context_pds3:investigation:mission.mars_express::1.0</lidvid_reference>
            <reference_type>has_mission</reference_type>
        </Internal_Reference>
        <Internal_Reference>
            <lidvid_reference>urn:nasa:pds:context_pds3:instrument_host:spacecraft.mex::1.0</lidvid_reference>
            <reference_type>has_instrument_host</reference_type>
        </Internal_Reference>
        <Internal_Reference>
            <lidvid_reference>urn:nasa:pds:context_pds3:instrument:omega.mex::1.0</lidvid_reference>
            <reference_type>has_instrument</reference_type>
        </Internal_Reference>
        <Internal_Reference>
            <lidvid_reference>urn:nasa:pds:context_pds3:target:planet.mars::1.0</lidvid_reference>
            <reference_type>has_target</reference_type>
        </Internal_Reference>
        <Internal_Reference>
            <lidvid_reference>urn:nasa:pds:context_pds3:target:satellite.deimos::1.0</lidvid_reference>
            <reference_type>has_target</reference_type>
        </Internal_Reference>
        <Internal_Reference>
            <lidvid_reference>urn:nasa:pds:context_pds3:target:satellite.phobos::1.0</lidvid_reference>
            <reference_type>has_target</reference_type>
        </Internal_Reference>
        <Internal_Reference>
            <lidvid_reference>urn:nasa:pds:context_pds3:resource:resource.mex-m-omega-2-edr-flight-v1.0__browserp_geo_mex-m-omega-2-edr-flight-v1.0::1.0</lidvid_reference>
            <reference_type>has_resource</reference_type>
        </Internal_Reference>
        <Internal_Reference>
            <lidvid_reference>urn:nasa:pds:context_pds3:resource:resource.mex-m-omega-2-edr-flight-v1.0__dvo_geo_mex-m-omega-2-edr-flight-v1.0::1.0</lidvid_reference>
            <reference_type>has_resource</reference_type>
        </Internal_Reference>
        <Internal_Reference>
            <lidvid_reference>urn:nasa:pds:context_pds3:node:node.psa::1.0</lidvid_reference>
            <reference_type>has_node</reference_type>
        </Internal_Reference>
        <External_Reference>
            <reference_text>
                   unk
            </reference_text>
            <description>reference.unk</description>
        </External_Reference>
    </Reference_List>
    
    <Data_Set_PDS3>
        <data_set_id>MEX-M-OMEGA-2-EDR-FLIGHT-V1.0</data_set_id>
        <data_set_name>OMEGA FLIGHT EXPERIMENT DATA RECORDS</data_set_name>
        <data_set_release_date>Unknown</data_set_release_date>
        <start_time>2004-01-01</start_time>
        <stop_time nilReason="unknown" xsi:nil="true"></stop_time>
        <producer_full_name>Gilles Poulleau</producer_full_name>
        <citation_text>
            Poulleau, G., Omega Flight Experiment Data Records,
            MEX-M-OMEGA-2-EDR-FLIGHT-V1.0, European Space Agency, 2006
        </citation_text>
        <data_set_terse_desc>
            Mars Express Omega Flight Experiment Data Records from cruise
            phase to end of mission.
        </data_set_terse_desc>
        <abstract_desc>Unknown</abstract_desc>
        <data_set_desc>
This dataset contains
                                       experiment data records
                                       acquired from the beginning of
                                       the cruise phase to the end of
                                       the Mars Express mission in
                                       orbit around Mars. The dataset
                                       also includes geometry data
                                       for each experiment data
                                       records.
        </data_set_desc>
        <confidence_level_note>
NULL
        </confidence_level_note>
        <archive_status>ARCHIVED_ACCUMULATING</archive_status>
        <NSSDC>
            <medium_type>ELECTRONIC</medium_type>
            <nssdc_collection_id>NULL</nssdc_collection_id>
        </NSSDC>
    </Data_Set_PDS3>
</Product_Data_Set_PDS3>

